pt14-3.14.0.dev1.dist-info/METADATA
pt14-3.14.0.dev1.dist-info/WHEEL
pt14-3.14.0.dev1.dist-info/entry_points.txt
pt14/__init__.py
pt14/app.py
pt14/fourteen/__init__.py
pt14-3.14.0.dev1.dist-info/RECORD
